{
  "alias": "【公共】构造实时网关流量",
  "case_id": 51422,
  "name": "【公共】构造实时网关流量",
  "description": "功能说明：该公共步骤主要用于 '【公共】构造实时网关流量' 操作。\n依赖入参：userid2test, password2test, userIp2test\n抛出变量：username, Acct-Session-Id, nasIP, userMac, userIP, onlineuuid, userTemplateUUID, packageuuid",
  "inputs": [
    {
      "name": "userid2test",
      "value": "autobyll028",
      "note": ""
    },
    {
      "name": "password2test",
      "value": "shyfzx@163",
      "note": ""
    },
    {
      "name": "userIp2test",
      "value": "10.2.2.21",
      "note": ""
    }
  ],
  "outputs": [
    {
      "name": "username",
      "expression": "1"
    },
    {
      "name": "Acct-Session-Id",
      "expression": "44"
    },
    {
      "name": "nasIP",
      "expression": "4"
    },
    {
      "name": "userMac",
      "expression": "31"
    },
    {
      "name": "userIP",
      "expression": "8"
    },
    {
      "name": "onlineuuid",
      "expression": "$.data.results[0].onlineUserUuid"
    },
    {
      "name": "userTemplateUUID",
      "expression": "$.data[?(@.userTemplateName == '自动化包月限网关流量-可变套餐')].userTemplateUuid[0]"
    },
    {
      "name": "packageuuid",
      "expression": "$.data[?(@.userPackageName == \"自动化网关流量20元包月限50G\")].userPackageAreaDTOS[0].userPackageAreaRuleDTOS[0].packageRuleUuid"
    }
  ]
}